<?xml version="1.0"?>
<localization>
    <strings section="EXCEPTION">
        <string key="E_BASE_SINGLETON_CLONED">It is not allowed to clone instances of \Savvy\Base\AbstractSingleton</string>

        <string key="E_COMPONENT_LOGGER_FACTORY_UNKNOWN_LOGGER">Specified logging facility "%s" does not exist</string>
        <string key="E_COMPONENT_UTILITY_EXECUTABLE_NOT_DEFINED">No executable binary specified</string>
        <string key="E_COMPONENT_UTILITY_EXECUTABLE_NOT_FOUND">Executable binary "%s" was not found</string>
        <string key="E_COMPONENT_AUTHENTICATOR_FACTORY_NO_FACILITY">No authentication facility available, check configuration</string>
        <string key="E_COMPONENT_AUTHENTICATOR_FACTORY_UNKNOWN_FACILITY">Unknown authentication facility "%s"</string>
        <string key="E_COMPONENT_TASK_FACTORY_CRON_EXPRESSION_INVALID">Invalid cron expression "%s"</string>
        <string key="E_COMPONENT_TASK_FACTORY_TASK_NOT_FOUND">Task not found "%s"</string>

        <string key="E_RUNNER_FACTORY_UNKNOWN_RUNNER">Failed to create apropriate runner instance</string>
        <string key="E_RUNNER_GUI_VIEW_NOT_FOUND">Requested view "%s" does not exist</string>
        <string key="E_RUNNER_GUI_ACTION_NOT_FOUND">Requested action "%s" does not exist</string>
        <string key="E_RUNNER_GUI_ACTION_NOT_FOUND">Requested action "%s" does not exist</string>
    </strings>

    <strings section="COMMON">
        <string key="BUTTON_CLOSE">Close</string>
        <string key="BUTTON_OPEN">Open</string>
        <string key="BUTTON_SHOW">Show</string>
        <string key="BUTTON_LOGOUT">Logout</string>
    </strings>

    <strings section="DAEMON">
        <string key="PIDFILE_WRITE_ERROR">Failed to create PID file "%s"</string>
        <string key="PIPEFILE_WRITE_ERROR">Failed to open or create named pipe file "%s"</string>
        <string key="UNKNOWN_COMMAND">Received unkown command "%s"</string>
        <string key="STARTED">Service daemon started (PID %d)</string>
        <string key="TERMINATED">Service daemon terminated</string>
        <string key="SCHEDULER_INITIALIZED">Scheduler initialized, %d task(s) active</string>
        <string key="SCHEDULER_RELOADED">Scheduler reloaded, %d task(s) active</string>
    </strings>
</localization>
